Metadata-Version: 1.1
Name: scikit-data
Version: 0.1.3
Summary: The propose of this library is to allow the data analysis process more easy and automatic.
Home-page: https://github.com/OpenDataScienceLab/skdata
Author: Ivan Ogasawara
Author-email: ivan.ogasawara@gmail.com
License: MIT license
Download-URL: https://github.com/OpenDataScienceLab/skdata/archive/master.tar.gz
Keywords: scikit data analysis
Platform: UNKNOWN
Classifier: Development Status :: 2 - Pre-Alpha
Classifier: Intended Audience :: Developers
Classifier: License :: OSI Approved :: MIT License
Classifier: Natural Language :: English
Classifier: Programming Language :: Python :: 3.4
Classifier: Programming Language :: Python :: 3.5
Classifier: Programming Language :: Python :: 3.6
